[
    {
        "group": null, 
        "task": "Don't worry, be happy :)", 
        "datetime": null, 
        "recurrence": null
    }, 
    {
        "group": [
            "Computer Science"
        ], 
        "task": "Do computer science reading", 
        "datetime": "12/17/21 15:49", 
        "recurrence": null
    }, 
    {
        "group": null, 
        "task": "Study for compsci", 
        "datetime": null, 
        "recurrence": null
    }, 
    {
        "group": [
            "Computer Science"
        ], 
        "task": "Work on cs lab", 
        "datetime": "12/16/21 18:00", 
        "recurrence": null
    }, 
    {
        "group": null, 
        "task": "Remind Deni to give cats flea meds", 
        "datetime": null, 
        "recurrence": "every month on the 18th"
    }, 
    {
        "group": [
            "Biology"
        ], 
        "task": "Start bio HW!!!", 
        "datetime": "12/12/21 21:00", 
        "recurrence": null
    }, 
    {
        "group": null, 
        "task": "Pick up books from lib", 
        "datetime": "12/16/21 15:49", 
        "recurrence": null
    }, 
    {
        "group": null, 
        "task": "Use leftover rice", 
        "datetime": "12/14/21 15:49", 
        "recurrence": null
    }, 
    {
        "group": null, 
        "task": "Go to class", 
        "datetime": "12/13/21 09:00", 
        "recurrence": null
    }, 
    {
        "group": null, 
        "task": "eat dinner", 
        "datetime": null, 
        "recurrence": null
    }, 
    {
        "group": null, 
        "task": null, 
        "datetime": null, 
        "recurrence": null
    }, 
    {
        "group": null, 
        "task": "Prepare for MarketBridge interview", 
        "datetime": "12/17/21 15:49", 
        "recurrence": null
    }, 
    {
        "group": [
            "Japanese"
        ], 
        "task": "practice japanese speech", 
        "datetime": "12/12/21 21:00", 
        "recurrence": null
    }, 
    {
        "group": null, 
        "task": "take medicine", 
        "datetime": null, 
        "recurrence": null
    }, 
    {
        "group": null, 
        "task": "DON'T LET THE DOG EAT THE HOMEWORK!!!", 
        "datetime": null, 
        "recurrence": null
    }, 
    {
        "group": null, 
        "task": "Go to the grocery store for food", 
        "datetime": "12/14/21 15:49", 
        "recurrence": null
    }, 
    {
        "group": null, 
        "task": "Take down the lights!", 
        "datetime": "12/12/21 15:49", 
        "recurrence": null
    }, 
    {
        "group": null, 
        "task": "do push-ups", 
        "datetime": null, 
        "recurrence": "every day this week"
    }, 
    {
        "group": null, 
        "task": "call friend", 
        "datetime": "12/26/21 15:49", 
        "recurrence": null
    }, 
    {
        "group": null, 
        "task": "take 1se video", 
        "datetime": null, 
        "recurrence": "every day at 12pm"
    }, 
    {
        "group": null, 
        "task": "go to work", 
        "datetime": "12/12/21 12:00", 
        "recurrence": null
    }, 
    {
        "group": null, 
        "task": "doctor's appointment on", 
        "datetime": null, 
        "recurrence": null
    }, 
    {
        "group": null, 
        "task": "NLP group meeting", 
        "datetime": "12/12/21 05:00", 
        "recurrence": null
    }, 
    {
        "group": null, 
        "task": "send email to recruiter", 
        "datetime": null, 
        "recurrence": null
    }, 
    {
        "group": null, 
        "task": "mail package", 
        "datetime": "01/01/22 09:00", 
        "recurrence": null
    }, 
    {
        "group": null, 
        "task": "hello, world!", 
        "datetime": null, 
        "recurrence": null
    }, 
    {
        "group": [
            "English"
        ], 
        "task": "Finish English paper", 
        "datetime": "12/16/21 09:00", 
        "recurrence": null
    }, 
    {
        "group": null, 
        "task": "Reminder to take antibiotic", 
        "datetime": null, 
        "recurrence": "8:00 PM every night for the next week"
    }, 
    {
        "group": null, 
        "task": "Send posters to print shop", 
        "datetime": "12/15/21 17:30", 
        "recurrence": null
    }, 
    {
        "group": null, 
        "task": "Grab Eggs on my way home from work", 
        "datetime": null, 
        "recurrence": null
    }, 
    {
        "group": null, 
        "task": "Is this thing on? I can't tell", 
        "datetime": null, 
        "recurrence": null
    }, 
    {
        "group": null, 
        "task": "this is a task", 
        "datetime": "12/12/21 09:00", 
        "recurrence": null
    }, 
    {
        "group": null, 
        "task": "go to class", 
        "datetime": null, 
        "recurrence": "every day until December 6th"
    }, 
    {
        "group": null, 
        "task": "Leave for the airport", 
        "datetime": "12/12/21 07:30", 
        "recurrence": null
    }, 
    {
        "group": null, 
        "task": "Add more test cases by", 
        "datetime": null, 
        "recurrence": null
    }, 
    {
        "group": null, 
        "task": "Water the plants", 
        "datetime": null, 
        "recurrence": "every day from 10 May until 20 May"
    }, 
    {
        "group": null, 
        "task": "Shower", 
        "datetime": null, 
        "recurrence": "every six days"
    }, 
    {
        "group": null, 
        "task": "Harass my neighbors", 
        "datetime": null, 
        "recurrence": "every 14th"
    }, 
    {
        "group": null, 
        "task": "Grind leetcode", 
        "datetime": null, 
        "recurrence": "every day for three weeks"
    }, 
    {
        "group": null, 
        "task": "work stuff", 
        "datetime": null, 
        "recurrence": "every third friday"
    }, 
    {
        "group": null, 
        "task": "blink", 
        "datetime": null, 
        "recurrence": "every 5 seconds"
    }, 
    {
        "group": [
            "Biology"
        ], 
        "task": "Do every page of my bio HW", 
        "datetime": null, 
        "recurrence": null
    }, 
    {
        "group": [
            "Computer Science", 
            "Japanese"
        ], 
        "task": "Do my combined japanese and cs HW", 
        "datetime": null, 
        "recurrence": null
    }, 
    {
        "group": null, 
        "task": "Do the dishes", 
        "datetime": null, 
        "recurrence": "thursdays"
    }, 
    {
        "group": null, 
        "task": "Do hw", 
        "datetime": null, 
        "recurrence": "every thursday"
    }, 
    {
        "group": null, 
        "task": "teehee ;)", 
        "datetime": null, 
        "recurrence": null
    }, 
    {
        "group": null, 
        "task": "!!, . wow!!! super cool :)))", 
        "datetime": null, 
        "recurrence": null
    }
]